pythonExpress/__init__.py
pythonExpress/http_server.py
pythonExpress/request.py
pythonExpress/response.py
pythonExpress/tcp.py
pythonExpress-1.0.1.dist-info/LICENSE
pythonExpress-1.0.1.dist-info/METADATA
pythonExpress-1.0.1.dist-info/WHEEL
pythonExpress-1.0.1.dist-info/top_level.txt
pythonExpress-1.0.1.dist-info/RECORD
