Metadata-Version: 2.1
Name: pythonExpress
Version: 1.0.1
Summary: Express like syntax to create servers in python
Home-page: https://github.com/Tilakraj0308/python-express
Author: Tilak raj
Author-email: tilakraj7050@gmail.com
Classifier: Programming Language :: Python :: 3
Classifier: License :: OSI Approved :: MIT License
Classifier: Operating System :: OS Independent
License-File: LICENSE
